lasertram/__init__.py
lasertram/lasertram.mplstyle
lasertram/calc/__init__.py
lasertram/calc/calc.py
lasertram/data/__init__.py
lasertram/data/computers_and_geosciences_examples/2022-05-10_LT_ready.xlsx
lasertram/data/computers_and_geosciences_examples/example_internal_std.xlsx
lasertram/data/computers_and_geosciences_examples/example_intervals.xlsx
lasertram/data/georem/laicpms_stds_tidy.xlsx
lasertram/helpers/__init__.py
lasertram/helpers/batch.py
lasertram/helpers/conversions.py
lasertram/helpers/formatting.py
lasertram/helpers/plotting.py
lasertram/helpers/preprocessing.py
lasertram/tram/__init__.py
lasertram/tram/tram.py
lasertram-1.0.4.dist-info/licenses/LICENSE
tests/conftest.py
tests/test_batch.py
tests/test_calc.py
tests/test_conversions.py
tests/test_formatting.py
tests/test_mplstyle.py
tests/test_notebooks.py
tests/test_plotting.py
tests/test_preprocessing.py
tests/test_tram.py
lasertram-1.0.4.dist-info/METADATA
lasertram-1.0.4.dist-info/WHEEL
lasertram-1.0.4.dist-info/entry_points.txt
lasertram-1.0.4.dist-info/top_level.txt
lasertram-1.0.4.dist-info/RECORD
