Metadata-Version: 2.4
Name: lasertram
Version: 1.0.4
Summary: For processing LA-ICP-MS data
Author-email: Jordan Lubbers <jelubber@gmail.com>
License: License
Project-URL: Repository, https://github.com/jlubbersgeo/lasertram.git
Project-URL: Documentation, https://jlubbersgeo.github.io/lasertram/
Project-URL: Changelog, https://jlubbersgeo.github.io/lasertram/CHANGELOG/
Keywords: laicpms,laser ablation,geochemistry,trace elements
Classifier: Development Status :: 4 - Beta
Classifier: Topic :: Scientific/Engineering
Classifier: Operating System :: OS Independent
Classifier: Programming Language :: Python :: 3
Classifier: Programming Language :: Python :: 3.10
Classifier: Programming Language :: Python :: 3.11
Classifier: Programming Language :: Python :: 3.12
Classifier: Programming Language :: Python :: 3.13
Requires-Python: >=3.10
License-File: LICENSE
Requires-Dist: numpy>=1.25.2
Requires-Dist: pandas>=2.0.3
Requires-Dist: scipy>=1.11.1
Requires-Dist: statsmodels>=0.14.0
Requires-Dist: openpyxl>=3.0.0
Requires-Dist: matplotlib
Requires-Dist: tabulate
Requires-Dist: tqdm
Dynamic: license-file
